Workbook

Sheet Extrato
A1: Configuração
A2: Iniciais
A3: Referência
A4: Saldo inicial
A5: Saldo final | B5: =B4+SUM(H9:H1004) -> 0
A7: Lançamentos | J7: Totais por natureza | M7: Lançamentos agrupados por natureza | Q7: Suporte 2 | AA7: Suporte 4
A8: Fonte | B8: Data | C8: Transcrição | D8: Ref. | E8: Iniciais | F8: Natureza | G8: Descrição | H8: Valor | J8: {=_xlfn.LET(_xlpm.nat,Tabela1[Natureza],_xlpm.hdr,_xlfn.HSTACK("Natureza","Somatória"),IF(SUM(--(_xlpm.nat<>""))=0,_xlpm.hdr,_xlfn.LET(_xlpm.u,_xlfn.UNIQUE(_xlfn._xlws.FILTER(_xlpm.nat,_xlpm.nat<>"")),_xlpm.k,IF(_xlpm.u="RR",0,_xlfn.XMATCH(_xlpm.u,_xlpm.u)),_xlpm.n,_xlfn.SORTBY(_xlpm.u,_xlpm.k,1),_xlpm.s,SUMIF(Tabela1[Natureza],_xlpm.n,Tabela1[Valor]),_xlfn.VSTACK(_xlpm.hdr,_xlfn.HSTACK(_xlpm.n,_xlpm.s),_xlfn.HSTACK("TOTAL >>>",SUM(_xlpm.s))))))} -> Natureza | K8: Somatória | M8: {=_xlfn.LET(_xlpm.natcol,Tabela1[Natureza],_xlpm.hdr,_xlfn.HSTACK("Natureza","Descrição","Valor"),IF(SUM(--(_xlpm.natcol<>""))=0,_xlpm.hdr,_xlfn.LET(_xlpm.d,_xlfn._xlws.FILTER(_xlfn.HSTACK(Tabela1[Natureza],Tabela1[Descrição],Tabela1[Valor]),_xlpm.natcol<>""),_xlpm.ordem,_xlfn.XMATCH(_xlfn.CHOOSECOLS(_xlpm.d,1),_xlfn.CHOOSECOLS(_xlfn.ANCHORARRAY(J8),1)),_xlpm.sorted,_xlfn.SORTBY(_xlpm.d,_xlpm.ordem,1,ABS(_xlfn.CHOOSECOLS(_xlpm.d,3)),-1),_xlpm.nat,_xlfn.CHOOSECOLS(_xlpm.sorted,1),_xlpm.r,ROWS(_xlpm.sorted),_xlpm.body,_xlfn.DROP(_xlfn.REDUCE(_xlfn.HSTACK("","",""),_xlfn.SEQUENCE(_xlpm.r),_xlfn.LAMBDA(_xlpm.acc,_xlpm.i,IF(AND(_xlpm.i>1,INDEX(_xlpm.nat,_xlpm.i)<>INDEX(_xlpm.nat,_xlpm.i-1)),_xlfn.VSTACK(_xlpm.acc,_xlfn.HSTACK("","",""),INDEX(_xlpm.sorted,_xlpm.i,0)),_xlfn.VSTACK(_xlpm.acc,INDEX(_xlpm.sorted,_xlpm.i,0))))),1),_xlfn.VSTACK(_xlpm.hdr,_xlpm.body))))} -> Natureza | N8: Descrição | O8: Valor | Q8: Mês | R8: Dia | S8: Caixa | T8: E/S | U8: Vlr | V8: Tipo | X8: Desc | Y8: Ass | AA8: Mês | AB8: Dia | AC8: Desc | AD8: Vlr | AF8: Ass
Q9: =IF($F9<>"",RIGHT(Tabela1[[#This Row],[Ref.]],2),"") | R9: =IF($F9<>"",1,"") | S9: =IF($F9<>"",_xlfn.XLOOKUP(F9,Naturezas!B:B,Naturezas!E:E,"",0,1),"") | T9: =IF($F9<>"",_xlfn.XLOOKUP($F9,Naturezas!B:B,Naturezas!D:D,"",0,1),"") | U9: =IF($F9<>"",IF(OR($F9=Naturezas!$B$3,$F9=Naturezas!$B$4,$F9=Naturezas!$B$5,$F9=Naturezas!$B$17,$F9=Naturezas!$B$18,$F9=Naturezas!$B$19),$H9,-$H9),"") | V9: =IF($F9<>"",$F9,"") | X9: =IF($F9<>"",$G9,"") | Y9: =IF($F9<>"",Tabela1[[#This Row],[Iniciais]],"") | AA9: =IF($F9<>"",RIGHT(Tabela1[[#This Row],[Ref.]],2),"") | AB9: =IF($F9<>"",DATE(LEFT(Tabela1[[#This Row],[Ref.]],4),RIGHT(Tabela1[[#This Row],[Ref.]],2),1),"") | AC9: =IF($F9<>"",$G9,"") | AD9: =IF($F9<>"",$H9,"") | AF9: =IF($F9<>"",$B$2,"")
Q10: =IF($F10<>"",RIGHT(Tabela1[[#This Row],[Ref.]],2),"") | R10: =IF($F10<>"",1,"") | S10: =IF($F10<>"",_xlfn.XLOOKUP(F10,Naturezas!B:B,Naturezas!E:E,"",0,1),"") | T10: =IF($F10<>"",_xlfn.XLOOKUP($F10,Naturezas!B:B,Naturezas!D:D,"",0,1),"") | U10: =IF(F10<>"",IF(OR(F10=Naturezas!$B$3,F10=Naturezas!$B$4,F10=Naturezas!$B$5,F10=Naturezas!$B$17,F10=Naturezas!$B$18,F10=Naturezas!$B$19),H10,-H10),"") | V10: =IF(F10<>"",F10,"") | X10: =IF(F10<>"",G10,"") | Y10: =IF(F10<>"",Tabela1[[#This Row],[Iniciais]],"") | AA10: =IF($F10<>"",RIGHT(Tabela1[[#This Row],[Ref.]],2),"") | AB10: =IF($F10<>"",DATE(LEFT(Tabela1[[#This Row],[Ref.]],4),RIGHT(Tabela1[[#This Row],[Ref.]],2),1),"") | AC10: =IF($F10<>"",$G10,"") | AD10: =IF($F10<>"",$H10,"") | AF10: =IF($F10<>"",$B$2,"")
Q11: =IF($F11<>"",RIGHT(Tabela1[[#This Row],[Ref.]],2),"") | R11: =IF($F11<>"",1,"") | S11: =IF($F11<>"",_xlfn.XLOOKUP(F11,Naturezas!B:B,Naturezas!E:E,"",0,1),"") | T11: =IF($F11<>"",_xlfn.XLOOKUP($F11,Naturezas!B:B,Naturezas!D:D,"",0,1),"") | U11: =IF(F11<>"",IF(OR(F11=Naturezas!$B$3,F11=Naturezas!$B$4,F11=Naturezas!$B$5,F11=Naturezas!$B$17,F11=Naturezas!$B$18,F11=Naturezas!$B$19),H11,-H11),"") | V11: =IF(F11<>"",F11,"") | X11: =IF(F11<>"",G11,"") | Y11: =IF(F11<>"",Tabela1[[#This Row],[Iniciais]],"") | AA11: =IF($F11<>"",RIGHT(Tabela1[[#This Row],[Ref.]],2),"") | AB11: =IF($F11<>"",DATE(LEFT(Tabela1[[#This Row],[Ref.]],4),RIGHT(Tabela1[[#This Row],[Ref.]],2),1),"") | AC11: =IF($F11<>"",$G11,"") | AD11: =IF($F11<>"",$H11,"") | AF11: =IF($F11<>"",$B$2,"")
Q12: =IF($F12<>"",RIGHT(Tabela1[[#This Row],[Ref.]],2),"") | R12: =IF($F12<>"",1,"") | S12: =IF($F12<>"",_xlfn.XLOOKUP(F12,Naturezas!B:B,Naturezas!E:E,"",0,1),"") | T12: =IF($F12<>"",_xlfn.XLOOKUP($F12,Naturezas!B:B,Naturezas!D:D,"",0,1),"") | U12: =IF(F12<>"",IF(OR(F12=Naturezas!$B$3,F12=Naturezas!$B$4,F12=Naturezas!$B$5,F12=Naturezas!$B$17,F12=Naturezas!$B$18,F12=Naturezas!$B$19),H12,-H12),"") | V12: =IF(F12<>"",F12,"") | X12: =IF(F12<>"",G12,"") | Y12: =IF(F12<>"",Tabela1[[#This Row],[Iniciais]],"") | AA12: =IF($F12<>"",RIGHT(Tabela1[[#This Row],[Ref.]],2),"") | AB12: =IF($F12<>"",DATE(LEFT(Tabela1[[#This Row],[Ref.]],4),RIGHT(Tabela1[[#This Row],[Ref.]],2),1),"") | AC12: =IF($F12<>"",$G12,"") | AD12: =IF($F12<>"",$H12,"") | AF12: =IF($F12<>"",$B$2,"")
Q13: =IF($F13<>"",RIGHT(Tabela1[[#This Row],[Ref.]],2),"") | R13: =IF($F13<>"",1,"") | S13: =IF($F13<>"",_xlfn.XLOOKUP(F13,Naturezas!B:B,Naturezas!E:E,"",0,1),"") | T13: =IF($F13<>"",_xlfn.XLOOKUP($F13,Naturezas!B:B,Naturezas!D:D,"",0,1),"") | U13: =IF(F13<>"",IF(OR(F13=Naturezas!$B$3,F13=Naturezas!$B$4,F13=Naturezas!$B$5,F13=Naturezas!$B$17,F13=Naturezas!$B$18,F13=Naturezas!$B$19),H13,-H13),"") | V13: =IF(F13<>"",F13,"") | X13: =IF(F13<>"",G13,"") | Y13: =IF(F13<>"",Tabela1[[#This Row],[Iniciais]],"") | AA13: =IF($F13<>"",RIGHT(Tabela1[[#This Row],[Ref.]],2),"") | AB13: =IF($F13<>"",DATE(LEFT(Tabela1[[#This Row],[Ref.]],4),RIGHT(Tabela1[[#This Row],[Ref.]],2),1),"") | AC13: =IF($F13<>"",$G13,"") | AD13: =IF($F13<>"",$H13,"") | AF13: =IF($F13<>"",$B$2,"")
Q14: =IF($F14<>"",RIGHT(Tabela1[[#This Row],[Ref.]],2),"") | R14: =IF($F14<>"",1,"") | S14: =IF($F14<>"",_xlfn.XLOOKUP(F14,Naturezas!B:B,Naturezas!E:E,"",0,1),"") | T14: =IF($F14<>"",_xlfn.XLOOKUP($F14,Naturezas!B:B,Naturezas!D:D,"",0,1),"") | U14: =IF(F14<>"",IF(OR(F14=Naturezas!$B$3,F14=Naturezas!$B$4,F14=Naturezas!$B$5,F14=Naturezas!$B$17,F14=Naturezas!$B$18,F14=Naturezas!$B$19),H14,-H14),"") | V14: =IF(F14<>"",F14,"") | X14: =IF(F14<>"",G14,"") | Y14: =IF(F14<>"",Tabela1[[#This Row],[Iniciais]],"") | AA14: =IF($F14<>"",RIGHT(Tabela1[[#This Row],[Ref.]],2),"") | AB14: =IF($F14<>"",DATE(LEFT(Tabela1[[#This Row],[Ref.]],4),RIGHT(Tabela1[[#This Row],[Ref.]],2),1),"") | AC14: =IF($F14<>"",$G14,"") | AD14: =IF($F14<>"",$H14,"") | AF14: =IF($F14<>"",$B$2,"")
Q15: =IF($F15<>"",RIGHT(Tabela1[[#This Row],[Ref.]],2),"") | R15: =IF($F15<>"",1,"") | S15: =IF($F15<>"",_xlfn.XLOOKUP(F15,Naturezas!B:B,Naturezas!E:E,"",0,1),"") | T15: =IF($F15<>"",_xlfn.XLOOKUP($F15,Naturezas!B:B,Naturezas!D:D,"",0,1),"") | U15: =IF(F15<>"",IF(OR(F15=Naturezas!$B$3,F15=Naturezas!$B$4,F15=Naturezas!$B$5,F15=Naturezas!$B$17,F15=Naturezas!$B$18,F15=Naturezas!$B$19),H15,-H15),"") | V15: =IF(F15<>"",F15,"") | X15: =IF(F15<>"",G15,"") | Y15: =IF(F15<>"",Tabela1[[#This Row],[Iniciais]],"") | AA15: =IF($F15<>"",RIGHT(Tabela1[[#This Row],[Ref.]],2),"") | AB15: =IF($F15<>"",DATE(LEFT(Tabela1[[#This Row],[Ref.]],4),RIGHT(Tabela1[[#This Row],[Ref.]],2),1),"") | AC15: =IF($F15<>"",$G15,"") | AD15: =IF($F15<>"",$H15,"") | AF15: =IF($F15<>"",$B$2,"")
Q16: =IF($F16<>"",RIGHT(Tabela1[[#This Row],[Ref.]],2),"") | R16: =IF($F16<>"",1,"") | S16: =IF($F16<>"",_xlfn.XLOOKUP(F16,Naturezas!B:B,Naturezas!E:E,"",0,1),"") | T16: =IF($F16<>"",_xlfn.XLOOKUP($F16,Naturezas!B:B,Naturezas!D:D,"",0,1),"") | U16: =IF(F16<>"",IF(OR(F16=Naturezas!$B$3,F16=Naturezas!$B$4,F16=Naturezas!$B$5,F16=Naturezas!$B$17,F16=Naturezas!$B$18,F16=Naturezas!$B$19),H16,-H16),"") | V16: =IF(F16<>"",F16,"") | X16: =IF(F16<>"",G16,"") | Y16: =IF(F16<>"",Tabela1[[#This Row],[Iniciais]],"") | AA16: =IF($F16<>"",RIGHT(Tabela1[[#This Row],[Ref.]],2),"") | AB16: =IF($F16<>"",DATE(LEFT(Tabela1[[#This Row],[Ref.]],4),RIGHT(Tabela1[[#This Row],[Ref.]],2),1),"") | AC16: =IF($F16<>"",$G16,"") | AD16: =IF($F16<>"",$H16,"") | AF16: =IF($F16<>"",$B$2,"")
Q17: =IF($F17<>"",RIGHT(Tabela1[[#This Row],[Ref.]],2),"") | R17: =IF($F17<>"",1,"") | S17: =IF($F17<>"",_xlfn.XLOOKUP(F17,Naturezas!B:B,Naturezas!E:E,"",0,1),"") | T17: =IF($F17<>"",_xlfn.XLOOKUP($F17,Naturezas!B:B,Naturezas!D:D,"",0,1),"") | U17: =IF(F17<>"",IF(OR(F17=Naturezas!$B$3,F17=Naturezas!$B$4,F17=Naturezas!$B$5,F17=Naturezas!$B$17,F17=Naturezas!$B$18,F17=Naturezas!$B$19),H17,-H17),"") | V17: =IF(F17<>"",F17,"") | X17: =IF(F17<>"",G17,"") | Y17: =IF(F17<>"",Tabela1[[#This Row],[Iniciais]],"") | AA17: =IF($F17<>"",RIGHT(Tabela1[[#This Row],[Ref.]],2),"") | AB17: =IF($F17<>"",DATE(LEFT(Tabela1[[#This Row],[Ref.]],4),RIGHT(Tabela1[[#This Row],[Ref.]],2),1),"") | AC17: =IF($F17<>"",$G17,"") | AD17: =IF($F17<>"",$H17,"") | AF17: =IF($F17<>"",$B$2,"")
Q18: =IF($F18<>"",RIGHT(Tabela1[[#This Row],[Ref.]],2),"") | R18: =IF($F18<>"",1,"") | S18: =IF($F18<>"",_xlfn.XLOOKUP(F18,Naturezas!B:B,Naturezas!E:E,"",0,1),"") | T18: =IF($F18<>"",_xlfn.XLOOKUP($F18,Naturezas!B:B,Naturezas!D:D,"",0,1),"") | U18: =IF(F18<>"",IF(OR(F18=Naturezas!$B$3,F18=Naturezas!$B$4,F18=Naturezas!$B$5,F18=Naturezas!$B$17,F18=Naturezas!$B$18,F18=Naturezas!$B$19),H18,-H18),"") | V18: =IF(F18<>"",F18,"") | X18: =IF(F18<>"",G18,"") | Y18: =IF(F18<>"",Tabela1[[#This Row],[Iniciais]],"") | AA18: =IF($F18<>"",RIGHT(Tabela1[[#This Row],[Ref.]],2),"") | AB18: =IF($F18<>"",DATE(LEFT(Tabela1[[#This Row],[Ref.]],4),RIGHT(Tabela1[[#This Row],[Ref.]],2),1),"") | AC18: =IF($F18<>"",$G18,"") | AD18: =IF($F18<>"",$H18,"") | AF18: =IF($F18<>"",$B$2,"")
Q19: =IF($F19<>"",RIGHT(Tabela1[[#This Row],[Ref.]],2),"") | R19: =IF($F19<>"",1,"") | S19: =IF($F19<>"",_xlfn.XLOOKUP(F19,Naturezas!B:B,Naturezas!E:E,"",0,1),"") | T19: =IF($F19<>"",_xlfn.XLOOKUP($F19,Naturezas!B:B,Naturezas!D:D,"",0,1),"") | U19: =IF(F19<>"",IF(OR(F19=Naturezas!$B$3,F19=Naturezas!$B$4,F19=Naturezas!$B$5,F19=Naturezas!$B$17,F19=Naturezas!$B$18,F19=Naturezas!$B$19),H19,-H19),"") | V19: =IF(F19<>"",F19,"") | X19: =IF(F19<>"",G19,"") | Y19: =IF(F19<>"",Tabela1[[#This Row],[Iniciais]],"") | AA19: =IF($F19<>"",RIGHT(Tabela1[[#This Row],[Ref.]],2),"") | AB19: =IF($F19<>"",DATE(LEFT(Tabela1[[#This Row],[Ref.]],4),RIGHT(Tabela1[[#This Row],[Ref.]],2),1),"") | AC19: =IF($F19<>"",$G19,"") | AD19: =IF($F19<>"",$H19,"") | AF19: =IF($F19<>"",$B$2,"")
Q20: =IF($F20<>"",RIGHT(Tabela1[[#This Row],[Ref.]],2),"") | R20: =IF($F20<>"",1,"") | S20: =IF($F20<>"",_xlfn.XLOOKUP(F20,Naturezas!B:B,Naturezas!E:E,"",0,1),"") | T20: =IF($F20<>"",_xlfn.XLOOKUP($F20,Naturezas!B:B,Naturezas!D:D,"",0,1),"") | U20: =IF(F20<>"",IF(OR(F20=Naturezas!$B$3,F20=Naturezas!$B$4,F20=Naturezas!$B$5,F20=Naturezas!$B$17,F20=Naturezas!$B$18,F20=Naturezas!$B$19),H20,-H20),"") | V20: =IF(F20<>"",F20,"") | X20: =IF(F20<>"",G20,"") | Y20: =IF(F20<>"",Tabela1[[#This Row],[Iniciais]],"") | AA20: =IF($F20<>"",RIGHT(Tabela1[[#This Row],[Ref.]],2),"") | AB20: =IF($F20<>"",DATE(LEFT(Tabela1[[#This Row],[Ref.]],4),RIGHT(Tabela1[[#This Row],[Ref.]],2),1),"") | AC20: =IF($F20<>"",$G20,"") | AD20: =IF($F20<>"",$H20,"") | AF20: =IF($F20<>"",$B$2,"")
Q21: =IF($F21<>"",RIGHT(Tabela1[[#This Row],[Ref.]],2),"") | R21: =IF($F21<>"",1,"") | S21: =IF($F21<>"",_xlfn.XLOOKUP(F21,Naturezas!B:B,Naturezas!E:E,"",0,1),"") | T21: =IF($F21<>"",_xlfn.XLOOKUP($F21,Naturezas!B:B,Naturezas!D:D,"",0,1),"") | U21: =IF(F21<>"",IF(OR(F21=Naturezas!$B$3,F21=Naturezas!$B$4,F21=Naturezas!$B$5,F21=Naturezas!$B$17,F21=Naturezas!$B$18,F21=Naturezas!$B$19),H21,-H21),"") | V21: =IF(F21<>"",F21,"") | X21: =IF(F21<>"",G21,"") | Y21: =IF(F21<>"",Tabela1[[#This Row],[Iniciais]],"") | AA21: =IF($F21<>"",RIGHT(Tabela1[[#This Row],[Ref.]],2),"") | AB21: =IF($F21<>"",DATE(LEFT(Tabela1[[#This Row],[Ref.]],4),RIGHT(Tabela1[[#This Row],[Ref.]],2),1),"") | AC21: =IF($F21<>"",$G21,"") | AD21: =IF($F21<>"",$H21,"") | AF21: =IF($F21<>"",$B$2,"")
... Q62: =IF($F62<>"",RIGHT(Tabela1[[#This Row],[Ref.]],2),"") | R62: =IF($F62<>"",1,"") | S62: =IF($F62<>"",_xlfn.XLOOKUP(F62,Naturezas!B:B,Naturezas!E:E,"",0,1),"") | T62: =IF($F62<>"",_xlfn.XLOOKUP($F62,Naturezas!B:B,Naturezas!D:D,"",0,1),"") | U62: =IF(F62<>"",IF(OR(F62=Naturezas!$B$3,F62=Naturezas!$B$4,F62=Naturezas!$B$5,F62=Naturezas!$B$17,F62=Naturezas!$B$18,F62=Naturezas!$B$19),H62,-H62),"") | V62: =IF(F62<>"",F62,"") | X62: =IF(F62<>"",G62,"") | Y62: =IF(F62<>"",Tabela1[[#This Row],[Iniciais]],"") | AA62: =IF($F62<>"",RIGHT(Tabela1[[#This Row],[Ref.]],2),"") | AB62: =IF($F62<>"",DATE(LEFT(Tabela1[[#This Row],[Ref.]],4),RIGHT(Tabela1[[#This Row],[Ref.]],2),1),"") | AC62: =IF($F62<>"",$G62,"") | AD62: =IF($F62<>"",$H62,"") | AF62: =IF($F62<>"",$B$2,"")
Q63: =IF($F63<>"",RIGHT(Tabela1[[#This Row],[Ref.]],2),"") | R63: =IF($F63<>"",1,"") | S63: =IF($F63<>"",_xlfn.XLOOKUP(F63,Naturezas!B:B,Naturezas!E:E,"",0,1),"") | T63: =IF($F63<>"",_xlfn.XLOOKUP($F63,Naturezas!B:B,Naturezas!D:D,"",0,1),"") | U63: =IF(F63<>"",IF(OR(F63=Naturezas!$B$3,F63=Naturezas!$B$4,F63=Naturezas!$B$5,F63=Naturezas!$B$17,F63=Naturezas!$B$18,F63=Naturezas!$B$19),H63,-H63),"") | V63: =IF(F63<>"",F63,"") | X63: =IF(F63<>"",G63,"") | Y63: =IF(F63<>"",Tabela1[[#This Row],[Iniciais]],"") | AA63: =IF($F63<>"",RIGHT(Tabela1[[#This Row],[Ref.]],2),"") | AB63: =IF($F63<>"",DATE(LEFT(Tabela1[[#This Row],[Ref.]],4),RIGHT(Tabela1[[#This Row],[Ref.]],2),1),"") | AC63: =IF($F63<>"",$G63,"") | AD63: =IF($F63<>"",$H63,"") | AF63: =IF($F63<>"",$B$2,"") | AJ63: Saldo cc | AK63: Aplic
Q64: =IF($F64<>"",RIGHT(Tabela1[[#This Row],[Ref.]],2),"") | R64: =IF($F64<>"",1,"") | S64: =IF($F64<>"",_xlfn.XLOOKUP(F64,Naturezas!B:B,Naturezas!E:E,"",0,1),"") | T64: =IF($F64<>"",_xlfn.XLOOKUP($F64,Naturezas!B:B,Naturezas!D:D,"",0,1),"") | U64: =IF(F64<>"",IF(OR(F64=Naturezas!$B$3,F64=Naturezas!$B$4,F64=Naturezas!$B$5,F64=Naturezas!$B$17,F64=Naturezas!$B$18,F64=Naturezas!$B$19),H64,-H64),"") | V64: =IF(F64<>"",F64,"") | X64: =IF(F64<>"",G64,"") | Y64: =IF(F64<>"",Tabela1[[#This Row],[Iniciais]],"") | AA64: =IF($F64<>"",RIGHT(Tabela1[[#This Row],[Ref.]],2),"") | AB64: =IF($F64<>"",DATE(LEFT(Tabela1[[#This Row],[Ref.]],4),RIGHT(Tabela1[[#This Row],[Ref.]],2),1),"") | AC64: =IF($F64<>"",$G64,"") | AD64: =IF($F64<>"",$H64,"") | AF64: =IF($F64<>"",$B$2,"") | AJ64: 198.48 | AK64: 279.94
Q65: =IF($F65<>"",RIGHT(Tabela1[[#This Row],[Ref.]],2),"") | R65: =IF($F65<>"",1,"") | S65: =IF($F65<>"",_xlfn.XLOOKUP(F65,Naturezas!B:B,Naturezas!E:E,"",0,1),"") | T65: =IF($F65<>"",_xlfn.XLOOKUP($F65,Naturezas!B:B,Naturezas!D:D,"",0,1),"") | U65: =IF(F65<>"",IF(OR(F65=Naturezas!$B$3,F65=Naturezas!$B$4,F65=Naturezas!$B$5,F65=Naturezas!$B$17,F65=Naturezas!$B$18,F65=Naturezas!$B$19),H65,-H65),"") | V65: =IF(F65<>"",F65,"") | X65: =IF(F65<>"",G65,"") | Y65: =IF(F65<>"",Tabela1[[#This Row],[Iniciais]],"") | AA65: =IF($F65<>"",RIGHT(Tabela1[[#This Row],[Ref.]],2),"") | AB65: =IF($F65<>"",DATE(LEFT(Tabela1[[#This Row],[Ref.]],4),RIGHT(Tabela1[[#This Row],[Ref.]],2),1),"") | AC65: =IF($F65<>"",$G65,"") | AD65: =IF($F65<>"",$H65,"") | AF65: =IF($F65<>"",$B$2,"")
Q66: =IF($F66<>"",RIGHT(Tabela1[[#This Row],[Ref.]],2),"") | R66: =IF($F66<>"",1,"") | S66: =IF($F66<>"",_xlfn.XLOOKUP(F66,Naturezas!B:B,Naturezas!E:E,"",0,1),"") | T66: =IF($F66<>"",_xlfn.XLOOKUP($F66,Naturezas!B:B,Naturezas!D:D,"",0,1),"") | U66: =IF(F66<>"",IF(OR(F66=Naturezas!$B$3,F66=Naturezas!$B$4,F66=Naturezas!$B$5,F66=Naturezas!$B$17,F66=Naturezas!$B$18,F66=Naturezas!$B$19),H66,-H66),"") | V66: =IF(F66<>"",F66,"") | X66: =IF(F66<>"",G66,"") | Y66: =IF(F66<>"",Tabela1[[#This Row],[Iniciais]],"") | AA66: =IF($F66<>"",RIGHT(Tabela1[[#This Row],[Ref.]],2),"") | AB66: =IF($F66<>"",DATE(LEFT(Tabela1[[#This Row],[Ref.]],4),RIGHT(Tabela1[[#This Row],[Ref.]],2),1),"") | AC66: =IF($F66<>"",$G66,"") | AD66: =IF($F66<>"",$H66,"") | AF66: =IF($F66<>"",$B$2,"")
Q67: =IF($F67<>"",RIGHT(Tabela1[[#This Row],[Ref.]],2),"") | R67: =IF($F67<>"",1,"") | S67: =IF($F67<>"",_xlfn.XLOOKUP(F67,Naturezas!B:B,Naturezas!E:E,"",0,1),"") | T67: =IF($F67<>"",_xlfn.XLOOKUP($F67,Naturezas!B:B,Naturezas!D:D,"",0,1),"") | U67: =IF(F67<>"",IF(OR(F67=Naturezas!$B$3,F67=Naturezas!$B$4,F67=Naturezas!$B$5,F67=Naturezas!$B$17,F67=Naturezas!$B$18,F67=Naturezas!$B$19),H67,-H67),"") | V67: =IF(F67<>"",F67,"") | X67: =IF(F67<>"",G67,"") | Y67: =IF(F67<>"",Tabela1[[#This Row],[Iniciais]],"") | AA67: =IF($F67<>"",RIGHT(Tabela1[[#This Row],[Ref.]],2),"") | AB67: =IF($F67<>"",DATE(LEFT(Tabela1[[#This Row],[Ref.]],4),RIGHT(Tabela1[[#This Row],[Ref.]],2),1),"") | AC67: =IF($F67<>"",$G67,"") | AD67: =IF($F67<>"",$H67,"") | AF67: =IF($F67<>"",$B$2,"")
Q68: =IF($F68<>"",RIGHT(Tabela1[[#This Row],[Ref.]],2),"") | R68: =IF($F68<>"",1,"") | S68: =IF($F68<>"",_xlfn.XLOOKUP(F68,Naturezas!B:B,Naturezas!E:E,"",0,1),"") | T68: =IF($F68<>"",_xlfn.XLOOKUP($F68,Naturezas!B:B,Naturezas!D:D,"",0,1),"") | U68: =IF(F68<>"",IF(OR(F68=Naturezas!$B$3,F68=Naturezas!$B$4,F68=Naturezas!$B$5,F68=Naturezas!$B$17,F68=Naturezas!$B$18,F68=Naturezas!$B$19),H68,-H68),"") | V68: =IF(F68<>"",F68,"") | X68: =IF(F68<>"",G68,"") | Y68: =IF(F68<>"",Tabela1[[#This Row],[Iniciais]],"") | AA68: =IF($F68<>"",RIGHT(Tabela1[[#This Row],[Ref.]],2),"") | AB68: =IF($F68<>"",DATE(LEFT(Tabela1[[#This Row],[Ref.]],4),RIGHT(Tabela1[[#This Row],[Ref.]],2),1),"") | AC68: =IF($F68<>"",$G68,"") | AD68: =IF($F68<>"",$H68,"") | AF68: =IF($F68<>"",$B$2,"")
Q69: =IF($F69<>"",RIGHT(Tabela1[[#This Row],[Ref.]],2),"") | R69: =IF($F69<>"",1,"") | S69: =IF($F69<>"",_xlfn.XLOOKUP(F69,Naturezas!B:B,Naturezas!E:E,"",0,1),"") | T69: =IF($F69<>"",_xlfn.XLOOKUP($F69,Naturezas!B:B,Naturezas!D:D,"",0,1),"") | U69: =IF(F69<>"",IF(OR(F69=Naturezas!$B$3,F69=Naturezas!$B$4,F69=Naturezas!$B$5,F69=Naturezas!$B$17,F69=Naturezas!$B$18,F69=Naturezas!$B$19),H69,-H69),"") | V69: =IF(F69<>"",F69,"") | X69: =IF(F69<>"",G69,"") | Y69: =IF(F69<>"",Tabela1[[#This Row],[Iniciais]],"") | AA69: =IF($F69<>"",RIGHT(Tabela1[[#This Row],[Ref.]],2),"") | AB69: =IF($F69<>"",DATE(LEFT(Tabela1[[#This Row],[Ref.]],4),RIGHT(Tabela1[[#This Row],[Ref.]],2),1),"") | AC69: =IF($F69<>"",$G69,"") | AD69: =IF($F69<>"",$H69,"") | AF69: =IF($F69<>"",$B$2,"")
Q70: =IF($F70<>"",RIGHT(Tabela1[[#This Row],[Ref.]],2),"") | R70: =IF($F70<>"",1,"") | S70: =IF($F70<>"",_xlfn.XLOOKUP(F70,Naturezas!B:B,Naturezas!E:E,"",0,1),"") | T70: =IF($F70<>"",_xlfn.XLOOKUP($F70,Naturezas!B:B,Naturezas!D:D,"",0,1),"") | U70: =IF(F70<>"",IF(OR(F70=Naturezas!$B$3,F70=Naturezas!$B$4,F70=Naturezas!$B$5,F70=Naturezas!$B$17,F70=Naturezas!$B$18,F70=Naturezas!$B$19),H70,-H70),"") | V70: =IF(F70<>"",F70,"") | X70: =IF(F70<>"",G70,"") | Y70: =IF(F70<>"",Tabela1[[#This Row],[Iniciais]],"") | AA70: =IF($F70<>"",RIGHT(Tabela1[[#This Row],[Ref.]],2),"") | AB70: =IF($F70<>"",DATE(LEFT(Tabela1[[#This Row],[Ref.]],4),RIGHT(Tabela1[[#This Row],[Ref.]],2),1),"") | AC70: =IF($F70<>"",$G70,"") | AD70: =IF($F70<>"",$H70,"") | AF70: =IF($F70<>"",$B$2,"")
Q71: =IF($F71<>"",RIGHT(Tabela1[[#This Row],[Ref.]],2),"") | R71: =IF($F71<>"",1,"") | S71: =IF($F71<>"",_xlfn.XLOOKUP(F71,Naturezas!B:B,Naturezas!E:E,"",0,1),"") | T71: =IF($F71<>"",_xlfn.XLOOKUP($F71,Naturezas!B:B,Naturezas!D:D,"",0,1),"") | U71: =IF(F71<>"",IF(OR(F71=Naturezas!$B$3,F71=Naturezas!$B$4,F71=Naturezas!$B$5,F71=Naturezas!$B$17,F71=Naturezas!$B$18,F71=Naturezas!$B$19),H71,-H71),"") | V71: =IF(F71<>"",F71,"") | X71: =IF(F71<>"",G71,"") | Y71: =IF(F71<>"",Tabela1[[#This Row],[Iniciais]],"") | AA71: =IF($F71<>"",RIGHT(Tabela1[[#This Row],[Ref.]],2),"") | AB71: =IF($F71<>"",DATE(LEFT(Tabela1[[#This Row],[Ref.]],4),RIGHT(Tabela1[[#This Row],[Ref.]],2),1),"") | AC71: =IF($F71<>"",$G71,"") | AD71: =IF($F71<>"",$H71,"") | AF71: =IF($F71<>"",$B$2,"")
Q72: =IF($F72<>"",RIGHT(Tabela1[[#This Row],[Ref.]],2),"") | R72: =IF($F72<>"",1,"") | S72: =IF($F72<>"",_xlfn.XLOOKUP(F72,Naturezas!B:B,Naturezas!E:E,"",0,1),"") | T72: =IF($F72<>"",_xlfn.XLOOKUP($F72,Naturezas!B:B,Naturezas!D:D,"",0,1),"") | U72: =IF(F72<>"",IF(OR(F72=Naturezas!$B$3,F72=Naturezas!$B$4,F72=Naturezas!$B$5,F72=Naturezas!$B$17,F72=Naturezas!$B$18,F72=Naturezas!$B$19),H72,-H72),"") | V72: =IF(F72<>"",F72,"") | X72: =IF(F72<>"",G72,"") | Y72: =IF(F72<>"",Tabela1[[#This Row],[Iniciais]],"") | AA72: =IF($F72<>"",RIGHT(Tabela1[[#This Row],[Ref.]],2),"") | AB72: =IF($F72<>"",DATE(LEFT(Tabela1[[#This Row],[Ref.]],4),RIGHT(Tabela1[[#This Row],[Ref.]],2),1),"") | AC72: =IF($F72<>"",$G72,"") | AD72: =IF($F72<>"",$H72,"") | AF72: =IF($F72<>"",$B$2,"")
Q73: =IF($F73<>"",RIGHT(Tabela1[[#This Row],[Ref.]],2),"") | R73: =IF($F73<>"",1,"") | S73: =IF($F73<>"",_xlfn.XLOOKUP(F73,Naturezas!B:B,Naturezas!E:E,"",0,1),"") | T73: =IF($F73<>"",_xlfn.XLOOKUP($F73,Naturezas!B:B,Naturezas!D:D,"",0,1),"") | U73: =IF(F73<>"",IF(OR(F73=Naturezas!$B$3,F73=Naturezas!$B$4,F73=Naturezas!$B$5,F73=Naturezas!$B$17,F73=Naturezas!$B$18,F73=Naturezas!$B$19),H73,-H73),"") | V73: =IF(F73<>"",F73,"") | X73: =IF(F73<>"",G73,"") | Y73: =IF(F73<>"",Tabela1[[#This Row],[Iniciais]],"") | AA73: =IF($F73<>"",RIGHT(Tabela1[[#This Row],[Ref.]],2),"") | AB73: =IF($F73<>"",DATE(LEFT(Tabela1[[#This Row],[Ref.]],4),RIGHT(Tabela1[[#This Row],[Ref.]],2),1),"") | AC73: =IF($F73<>"",$G73,"") | AD73: =IF($F73<>"",$H73,"") | AF73: =IF($F73<>"",$B$2,"")
Q74: =IF($F74<>"",RIGHT(Tabela1[[#This Row],[Ref.]],2),"") | R74: =IF($F74<>"",1,"") | S74: =IF($F74<>"",_xlfn.XLOOKUP(F74,Naturezas!B:B,Naturezas!E:E,"",0,1),"") | T74: =IF($F74<>"",_xlfn.XLOOKUP($F74,Naturezas!B:B,Naturezas!D:D,"",0,1),"") | U74: =IF(F74<>"",IF(OR(F74=Naturezas!$B$3,F74=Naturezas!$B$4,F74=Naturezas!$B$5,F74=Naturezas!$B$17,F74=Naturezas!$B$18,F74=Naturezas!$B$19),H74,-H74),"") | V74: =IF(F74<>"",F74,"") | X74: =IF(F74<>"",G74,"") | Y74: =IF(F74<>"",Tabela1[[#This Row],[Iniciais]],"") | AA74: =IF($F74<>"",RIGHT(Tabela1[[#This Row],[Ref.]],2),"") | AB74: =IF($F74<>"",DATE(LEFT(Tabela1[[#This Row],[Ref.]],4),RIGHT(Tabela1[[#This Row],[Ref.]],2),1),"") | AC74: =IF($F74<>"",$G74,"") | AD74: =IF($F74<>"",$H74,"") | AF74: =IF($F74<>"",$B$2,"")
Q75: =IF($F75<>"",RIGHT(Tabela1[[#This Row],[Ref.]],2),"") | R75: =IF($F75<>"",1,"") | S75: =IF($F75<>"",_xlfn.XLOOKUP(F75,Naturezas!B:B,Naturezas!E:E,"",0,1),"") | T75: =IF($F75<>"",_xlfn.XLOOKUP($F75,Naturezas!B:B,Naturezas!D:D,"",0,1),"") | U75: =IF(F75<>"",IF(OR(F75=Naturezas!$B$3,F75=Naturezas!$B$4,F75=Naturezas!$B$5,F75=Naturezas!$B$17,F75=Naturezas!$B$18,F75=Naturezas!$B$19),H75,-H75),"") | V75: =IF(F75<>"",F75,"") | X75: =IF(F75<>"",G75,"") | Y75: =IF(F75<>"",Tabela1[[#This Row],[Iniciais]],"") | AA75: =IF($F75<>"",RIGHT(Tabela1[[#This Row],[Ref.]],2),"") | AB75: =IF($F75<>"",DATE(LEFT(Tabela1[[#This Row],[Ref.]],4),RIGHT(Tabela1[[#This Row],[Ref.]],2),1),"") | AC75: =IF($F75<>"",$G75,"") | AD75: =IF($F75<>"",$H75,"") | AF75: =IF($F75<>"",$B$2,"")
Q76: =IF($F76<>"",RIGHT(Tabela1[[#This Row],[Ref.]],2),"") | R76: =IF($F76<>"",1,"") | S76: =IF($F76<>"",_xlfn.XLOOKUP(F76,Naturezas!B:B,Naturezas!E:E,"",0,1),"") | T76: =IF($F76<>"",_xlfn.XLOOKUP($F76,Naturezas!B:B,Naturezas!D:D,"",0,1),"") | U76: =IF(F76<>"",IF(OR(F76=Naturezas!$B$3,F76=Naturezas!$B$4,F76=Naturezas!$B$5,F76=Naturezas!$B$17,F76=Naturezas!$B$18,F76=Naturezas!$B$19),H76,-H76),"") | V76: =IF(F76<>"",F76,"") | X76: =IF(F76<>"",G76,"") | Y76: =IF(F76<>"",Tabela1[[#This Row],[Iniciais]],"") | AA76: =IF($F76<>"",RIGHT(Tabela1[[#This Row],[Ref.]],2),"") | AB76: =IF($F76<>"",DATE(LEFT(Tabela1[[#This Row],[Ref.]],4),RIGHT(Tabela1[[#This Row],[Ref.]],2),1),"") | AC76: =IF($F76<>"",$G76,"") | AD76: =IF($F76<>"",$H76,"") | AF76: =IF($F76<>"",$B$2,"")
... Q504: =IF($F504<>"",RIGHT(Tabela1[[#This Row],[Ref.]],2),"") | R504: =IF($F504<>"",1,"") | S504: =IF($F504<>"",_xlfn.XLOOKUP(F504,Naturezas!B:B,Naturezas!E:E,"",0,1),"") | T504: =IF($F504<>"",_xlfn.XLOOKUP($F504,Naturezas!B:B,Naturezas!D:D,"",0,1),"") | U504: =IF(F504<>"",IF(OR(F504=Naturezas!$B$3,F504=Naturezas!$B$4,F504=Naturezas!$B$5,F504=Naturezas!$B$17,F504=Naturezas!$B$18,F504=Naturezas!$B$19),H504,-H504),"") | V504: =IF(F504<>"",F504,"") | X504: =IF(F504<>"",G504,"") | Y504: =IF(F504<>"",Tabela1[[#This Row],[Iniciais]],"") | AA504: =IF($F504<>"",RIGHT(Tabela1[[#This Row],[Ref.]],2),"") | AB504: =IF($F504<>"",DATE(LEFT(Tabela1[[#This Row],[Ref.]],4),RIGHT(Tabela1[[#This Row],[Ref.]],2),1),"") | AC504: =IF($F504<>"",$G504,"") | AD504: =IF($F504<>"",$H504,"") | AF504: =IF($F504<>"",$B$2,"")

Sheet Dicionario

Sheet Naturezas
A1: Suporte
A2: Natureza | B2: Natureza | C2: E/S | D2: Dados de apoio | E2: Dados de apoio | F2: Descrição curta
A3: Residentes | B3: RR | C3: entrada | D3: E | E3: B | F3: Receitas e despesas vinculadas ao trabalho profissional e previdência privada
A4: Adjuntos | B4: AR | C4: entrada | D4: E | E4: B
A5: Subvenções | B5: DN | C5: entrada | D5: E | E5: B
A6: Pensões | B6: PS | C6: saída | D6: S | E6: B
A7: Gastos Ordinários | B7: GO | C7: saída | D7: S | E7: B | F7: Gastos ordinários (assinaturas, transporte, refeições, etc.)
A8: Roupas | B8: RP | C8: saída | D8: S | E8: B | F8: Gastos com roupas, sapatos, indumentária em geral
A9: Médicos e Remédios | B9: MR | C9: saída | D9: S | E9: B | F9: Gastos com consultas, exames, remédios, tratamentos, plano de saúde etc.
A10: Diversos Pessoais | B10: DV | C10: saída | D10: S | E10: B | F10: Gastos com cursos anuais, convívios, retiros, viagens, despesas extraordinárias etc.
A11: Adjuntos | B11: AD | C11: saída | D11: S | E11: B
A12: Veículos | B12: VC | C12: saída | D12: S | E12: B | F12: Gastos com combustível, pedágio, limpeza, manutenção, etc.
A13: Natal e Festas | B13: NF | C13: saída | D13: S | E13: B
A14: Vários | B14: VR | C14: saída | D14: S | E14: B | F14: Materiais de escritório
A15: Donativos ao Centro | B15: DC | C15: saída | D15: S | E15: B
A16: Contrib. labores ap. | B16: DL | C16: saída | D16: S | E16: B | F16: Subvenções e doações para iniciativas apostólicas, ajudas familiares etc.
A17: Contribuição de residentes | B17: CO | C17: entrada | D17: E | E17: C
A18: Contribuições participantes | B18: CP | C18: entrada | D18: E | E18: C
A19: Outros conceitos | B19: OT | C19: entrada | D19: E | E19: C
A20: IPTU e Seguros | B20: CF | C20: saída | D20: S | E20: C
A21: Ordenados | B21: OR | C21: saída | D21: S | E21: C | F21: Pagamento de ordenados
A22: Comestíveis | B22: CM | C22: saída | D22: S | E22: C | F22: Pagamento de despesas com comestiveis para a casa em geral
A23: Gastos Gerais | B23: GG | C23: saída | D23: S | E23: C
A24: Luz | B24: LZ | C24: saída | D24: S | E24: C | F24: Conta de energia
A25: Água | B25: AG | C25: saída | D25: S | E25: C | F25: Conta de água
A26: Gás | B26: GS | C26: saída | D26: S | E26: C | F26: Conta de gás
A27: Telefone | B27: TF | C27: saída | D27: S | E27: C | F27: Conta de internet e telefonia
A28: Consertos | B28: CS | C28: saída | D28: S | E28: C | F28: Custos com manutenção
A29: Manutenção/Reposição | B29: MT | C29: saída | D29: S | E29: C | F29: Custos com jardinagem, faxina, materiais de limpeza, peças e insumos para manutenção etc.
A30: Vários | B30: VR | C30: saída | D30: S | E30: C
A31: Atividades culturais | B31: AC | C31: saída | D31: S | E31: C
A32: Instalações | B32: IT | C32: saída | D32: S | E32: C | F32: Custos para consertos e melhorias em geral nas instalações da casa
