Workbook

Sheet Extrato
A1: Configuração
A2: Iniciais
A3: Referência
A4: Saldo inicial
A5: Saldo final | B5: =B4+SUM(G9:G1004) -> 0
A7: Lançamentos | K7: Totais por natureza | N7: Lançamentos agrupados por natureza | R7: Suporte 2 | AB7: Suporte 4
A8: Fonte | B8: Data | C8: Transcrição | D8: Ref. | E8: Mês | F8: Descrição | G8: Valor | H8: Natureza | I8: Iniciais | K8: {=_xlfn.LET(_xlpm.nat,Tabela1[Natureza],_xlpm.hdr,_xlfn.HSTACK("Natureza","Somatória"),IF(SUM(--(_xlpm.nat<>""))=0,_xlpm.hdr,_xlfn.LET(_xlpm.u,_xlfn.UNIQUE(_xlfn._xlws.FILTER(_xlpm.nat,_xlpm.nat<>"")),_xlpm.k,IF(_xlpm.u="RR",0,_xlfn.XMATCH(_xlpm.u,_xlpm.u)),_xlpm.n,_xlfn.SORTBY(_xlpm.u,_xlpm.k,1),_xlpm.s,SUMIF(Tabela1[Natureza],_xlpm.n,Tabela1[Valor]),_xlfn.VSTACK(_xlpm.hdr,_xlfn.HSTACK(_xlpm.n,_xlpm.s),_xlfn.HSTACK("TOTAL >>>",SUM(_xlpm.s))))))} -> Natureza | L8: Somatória | N8: {=_xlfn.LET(_xlpm.natcol,Tabela1[Natureza],_xlpm.hdr,_xlfn.HSTACK("Natureza","Descrição","Valor"),IF(SUM(--(_xlpm.natcol<>""))=0,_xlpm.hdr,_xlfn.LET(_xlpm.d,_xlfn._xlws.FILTER(_xlfn.HSTACK(Tabela1[Natureza],Tabela1[Descrição],Tabela1[Valor]),_xlpm.natcol<>""),_xlpm.ordem,_xlfn.XMATCH(_xlfn.CHOOSECOLS(_xlpm.d,1),_xlfn.CHOOSECOLS(_xlfn.ANCHORARRAY(K8),1)),_xlpm.sorted,_xlfn.SORTBY(_xlpm.d,_xlpm.ordem,1,ABS(_xlfn.CHOOSECOLS(_xlpm.d,3)),-1),_xlpm.nat,_xlfn.CHOOSECOLS(_xlpm.sorted,1),_xlpm.r,ROWS(_xlpm.sorted),_xlpm.body,_xlfn.DROP(_xlfn.REDUCE(_xlfn.HSTACK("","",""),_xlfn.SEQUENCE(_xlpm.r),_xlfn.LAMBDA(_xlpm.acc,_xlpm.i,IF(AND(_xlpm.i>1,INDEX(_xlpm.nat,_xlpm.i)<>INDEX(_xlpm.nat,_xlpm.i-1)),_xlfn.VSTACK(_xlpm.acc,_xlfn.HSTACK("","",""),INDEX(_xlpm.sorted,_xlpm.i,0)),_xlfn.VSTACK(_xlpm.acc,INDEX(_xlpm.sorted,_xlpm.i,0))))),1),_xlfn.VSTACK(_xlpm.hdr,_xlpm.body))))} -> Natureza | O8: Descrição | P8: Valor | R8: Mês | S8: Dia | T8: Caixa | U8: E/S | V8: Vlr | W8: Tipo | Y8: Desc | Z8: Ass | AB8: Mês | AC8: Dia | AD8: Desc | AE8: Vlr | AG8: Ass
R9: =IF($H9<>"",RIGHT(Tabela1[[#This Row],[Ref.]],2),"") | S9: =IF($H9<>"",1,"") | T9: =IF($H9<>"",_xlfn.XLOOKUP(H9,Naturezas!B:B,Naturezas!E:E,"",0,1),"") | U9: =IF($H9<>"",_xlfn.XLOOKUP($H9,Naturezas!B:B,Naturezas!D:D,"",0,1),"") | V9: =IF($H9<>"",IF(OR($H9=Naturezas!$B$3,$H9=Naturezas!$B$4,$H9=Naturezas!$B$5,$H9=Naturezas!$B$17,$H9=Naturezas!$B$18,$H9=Naturezas!$B$19),$G9,-$G9),"") | W9: =IF($H9<>"",$H9,"") | Y9: =IF($H9<>"",$F9,"") | Z9: =IF($H9<>"",Tabela1[[#This Row],[Iniciais]],"") | AB9: =IF($H9<>"",RIGHT(Tabela1[[#This Row],[Ref.]],2),"") | AC9: =IF($H9<>"",DATE(LEFT(Tabela1[[#This Row],[Ref.]],4),RIGHT(Tabela1[[#This Row],[Ref.]],2),1),"") | AD9: =IF($H9<>"",$F9,"") | AE9: =IF($H9<>"",$G9,"") | AG9: =IF($H9<>"",$B$2,"")
R10: =IF($H10<>"",RIGHT(Tabela1[[#This Row],[Ref.]],2),"") | S10: =IF($H10<>"",1,"") | T10: =IF($H10<>"",_xlfn.XLOOKUP(H10,Naturezas!B:B,Naturezas!E:E,"",0,1),"") | U10: =IF($H10<>"",_xlfn.XLOOKUP($H10,Naturezas!B:B,Naturezas!D:D,"",0,1),"") | V10: =IF(H10<>"",IF(OR(H10=Naturezas!$B$3,H10=Naturezas!$B$4,H10=Naturezas!$B$5,H10=Naturezas!$B$17,H10=Naturezas!$B$18,H10=Naturezas!$B$19),G10,-G10),"") | W10: =IF(H10<>"",H10,"") | Y10: =IF(H10<>"",F10,"") | Z10: =IF(H10<>"",Tabela1[[#This Row],[Iniciais]],"") | AB10: =IF($H10<>"",RIGHT(Tabela1[[#This Row],[Ref.]],2),"") | AC10: =IF($H10<>"",DATE(LEFT(Tabela1[[#This Row],[Ref.]],4),RIGHT(Tabela1[[#This Row],[Ref.]],2),1),"") | AD10: =IF($H10<>"",$F10,"") | AE10: =IF($H10<>"",$G10,"") | AG10: =IF($H10<>"",$B$2,"")
R11: =IF($H11<>"",RIGHT(Tabela1[[#This Row],[Ref.]],2),"") | S11: =IF($H11<>"",1,"") | T11: =IF($H11<>"",_xlfn.XLOOKUP(H11,Naturezas!B:B,Naturezas!E:E,"",0,1),"") | U11: =IF($H11<>"",_xlfn.XLOOKUP($H11,Naturezas!B:B,Naturezas!D:D,"",0,1),"") | V11: =IF(H11<>"",IF(OR(H11=Naturezas!$B$3,H11=Naturezas!$B$4,H11=Naturezas!$B$5,H11=Naturezas!$B$17,H11=Naturezas!$B$18,H11=Naturezas!$B$19),G11,-G11),"") | W11: =IF(H11<>"",H11,"") | Y11: =IF(H11<>"",F11,"") | Z11: =IF(H11<>"",Tabela1[[#This Row],[Iniciais]],"") | AB11: =IF($H11<>"",RIGHT(Tabela1[[#This Row],[Ref.]],2),"") | AC11: =IF($H11<>"",DATE(LEFT(Tabela1[[#This Row],[Ref.]],4),RIGHT(Tabela1[[#This Row],[Ref.]],2),1),"") | AD11: =IF($H11<>"",$F11,"") | AE11: =IF($H11<>"",$G11,"") | AG11: =IF($H11<>"",$B$2,"")
R12: =IF($H12<>"",RIGHT(Tabela1[[#This Row],[Ref.]],2),"") | S12: =IF($H12<>"",1,"") | T12: =IF($H12<>"",_xlfn.XLOOKUP(H12,Naturezas!B:B,Naturezas!E:E,"",0,1),"") | U12: =IF($H12<>"",_xlfn.XLOOKUP($H12,Naturezas!B:B,Naturezas!D:D,"",0,1),"") | V12: =IF(H12<>"",IF(OR(H12=Naturezas!$B$3,H12=Naturezas!$B$4,H12=Naturezas!$B$5,H12=Naturezas!$B$17,H12=Naturezas!$B$18,H12=Naturezas!$B$19),G12,-G12),"") | W12: =IF(H12<>"",H12,"") | Y12: =IF(H12<>"",F12,"") | Z12: =IF(H12<>"",Tabela1[[#This Row],[Iniciais]],"") | AB12: =IF($H12<>"",RIGHT(Tabela1[[#This Row],[Ref.]],2),"") | AC12: =IF($H12<>"",DATE(LEFT(Tabela1[[#This Row],[Ref.]],4),RIGHT(Tabela1[[#This Row],[Ref.]],2),1),"") | AD12: =IF($H12<>"",$F12,"") | AE12: =IF($H12<>"",$G12,"") | AG12: =IF($H12<>"",$B$2,"")
R13: =IF($H13<>"",RIGHT(Tabela1[[#This Row],[Ref.]],2),"") | S13: =IF($H13<>"",1,"") | T13: =IF($H13<>"",_xlfn.XLOOKUP(H13,Naturezas!B:B,Naturezas!E:E,"",0,1),"") | U13: =IF($H13<>"",_xlfn.XLOOKUP($H13,Naturezas!B:B,Naturezas!D:D,"",0,1),"") | V13: =IF(H13<>"",IF(OR(H13=Naturezas!$B$3,H13=Naturezas!$B$4,H13=Naturezas!$B$5,H13=Naturezas!$B$17,H13=Naturezas!$B$18,H13=Naturezas!$B$19),G13,-G13),"") | W13: =IF(H13<>"",H13,"") | Y13: =IF(H13<>"",F13,"") | Z13: =IF(H13<>"",Tabela1[[#This Row],[Iniciais]],"") | AB13: =IF($H13<>"",RIGHT(Tabela1[[#This Row],[Ref.]],2),"") | AC13: =IF($H13<>"",DATE(LEFT(Tabela1[[#This Row],[Ref.]],4),RIGHT(Tabela1[[#This Row],[Ref.]],2),1),"") | AD13: =IF($H13<>"",$F13,"") | AE13: =IF($H13<>"",$G13,"") | AG13: =IF($H13<>"",$B$2,"")
R14: =IF($H14<>"",RIGHT(Tabela1[[#This Row],[Ref.]],2),"") | S14: =IF($H14<>"",1,"") | T14: =IF($H14<>"",_xlfn.XLOOKUP(H14,Naturezas!B:B,Naturezas!E:E,"",0,1),"") | U14: =IF($H14<>"",_xlfn.XLOOKUP($H14,Naturezas!B:B,Naturezas!D:D,"",0,1),"") | V14: =IF(H14<>"",IF(OR(H14=Naturezas!$B$3,H14=Naturezas!$B$4,H14=Naturezas!$B$5,H14=Naturezas!$B$17,H14=Naturezas!$B$18,H14=Naturezas!$B$19),G14,-G14),"") | W14: =IF(H14<>"",H14,"") | Y14: =IF(H14<>"",F14,"") | Z14: =IF(H14<>"",Tabela1[[#This Row],[Iniciais]],"") | AB14: =IF($H14<>"",RIGHT(Tabela1[[#This Row],[Ref.]],2),"") | AC14: =IF($H14<>"",DATE(LEFT(Tabela1[[#This Row],[Ref.]],4),RIGHT(Tabela1[[#This Row],[Ref.]],2),1),"") | AD14: =IF($H14<>"",$F14,"") | AE14: =IF($H14<>"",$G14,"") | AG14: =IF($H14<>"",$B$2,"")
R15: =IF($H15<>"",RIGHT(Tabela1[[#This Row],[Ref.]],2),"") | S15: =IF($H15<>"",1,"") | T15: =IF($H15<>"",_xlfn.XLOOKUP(H15,Naturezas!B:B,Naturezas!E:E,"",0,1),"") | U15: =IF($H15<>"",_xlfn.XLOOKUP($H15,Naturezas!B:B,Naturezas!D:D,"",0,1),"") | V15: =IF(H15<>"",IF(OR(H15=Naturezas!$B$3,H15=Naturezas!$B$4,H15=Naturezas!$B$5,H15=Naturezas!$B$17,H15=Naturezas!$B$18,H15=Naturezas!$B$19),G15,-G15),"") | W15: =IF(H15<>"",H15,"") | Y15: =IF(H15<>"",F15,"") | Z15: =IF(H15<>"",Tabela1[[#This Row],[Iniciais]],"") | AB15: =IF($H15<>"",RIGHT(Tabela1[[#This Row],[Ref.]],2),"") | AC15: =IF($H15<>"",DATE(LEFT(Tabela1[[#This Row],[Ref.]],4),RIGHT(Tabela1[[#This Row],[Ref.]],2),1),"") | AD15: =IF($H15<>"",$F15,"") | AE15: =IF($H15<>"",$G15,"") | AG15: =IF($H15<>"",$B$2,"")
R16: =IF($H16<>"",RIGHT(Tabela1[[#This Row],[Ref.]],2),"") | S16: =IF($H16<>"",1,"") | T16: =IF($H16<>"",_xlfn.XLOOKUP(H16,Naturezas!B:B,Naturezas!E:E,"",0,1),"") | U16: =IF($H16<>"",_xlfn.XLOOKUP($H16,Naturezas!B:B,Naturezas!D:D,"",0,1),"") | V16: =IF(H16<>"",IF(OR(H16=Naturezas!$B$3,H16=Naturezas!$B$4,H16=Naturezas!$B$5,H16=Naturezas!$B$17,H16=Naturezas!$B$18,H16=Naturezas!$B$19),G16,-G16),"") | W16: =IF(H16<>"",H16,"") | Y16: =IF(H16<>"",F16,"") | Z16: =IF(H16<>"",Tabela1[[#This Row],[Iniciais]],"") | AB16: =IF($H16<>"",RIGHT(Tabela1[[#This Row],[Ref.]],2),"") | AC16: =IF($H16<>"",DATE(LEFT(Tabela1[[#This Row],[Ref.]],4),RIGHT(Tabela1[[#This Row],[Ref.]],2),1),"") | AD16: =IF($H16<>"",$F16,"") | AE16: =IF($H16<>"",$G16,"") | AG16: =IF($H16<>"",$B$2,"")
R17: =IF($H17<>"",RIGHT(Tabela1[[#This Row],[Ref.]],2),"") | S17: =IF($H17<>"",1,"") | T17: =IF($H17<>"",_xlfn.XLOOKUP(H17,Naturezas!B:B,Naturezas!E:E,"",0,1),"") | U17: =IF($H17<>"",_xlfn.XLOOKUP($H17,Naturezas!B:B,Naturezas!D:D,"",0,1),"") | V17: =IF(H17<>"",IF(OR(H17=Naturezas!$B$3,H17=Naturezas!$B$4,H17=Naturezas!$B$5,H17=Naturezas!$B$17,H17=Naturezas!$B$18,H17=Naturezas!$B$19),G17,-G17),"") | W17: =IF(H17<>"",H17,"") | Y17: =IF(H17<>"",F17,"") | Z17: =IF(H17<>"",Tabela1[[#This Row],[Iniciais]],"") | AB17: =IF($H17<>"",RIGHT(Tabela1[[#This Row],[Ref.]],2),"") | AC17: =IF($H17<>"",DATE(LEFT(Tabela1[[#This Row],[Ref.]],4),RIGHT(Tabela1[[#This Row],[Ref.]],2),1),"") | AD17: =IF($H17<>"",$F17,"") | AE17: =IF($H17<>"",$G17,"") | AG17: =IF($H17<>"",$B$2,"")
R18: =IF($H18<>"",RIGHT(Tabela1[[#This Row],[Ref.]],2),"") | S18: =IF($H18<>"",1,"") | T18: =IF($H18<>"",_xlfn.XLOOKUP(H18,Naturezas!B:B,Naturezas!E:E,"",0,1),"") | U18: =IF($H18<>"",_xlfn.XLOOKUP($H18,Naturezas!B:B,Naturezas!D:D,"",0,1),"") | V18: =IF(H18<>"",IF(OR(H18=Naturezas!$B$3,H18=Naturezas!$B$4,H18=Naturezas!$B$5,H18=Naturezas!$B$17,H18=Naturezas!$B$18,H18=Naturezas!$B$19),G18,-G18),"") | W18: =IF(H18<>"",H18,"") | Y18: =IF(H18<>"",F18,"") | Z18: =IF(H18<>"",Tabela1[[#This Row],[Iniciais]],"") | AB18: =IF($H18<>"",RIGHT(Tabela1[[#This Row],[Ref.]],2),"") | AC18: =IF($H18<>"",DATE(LEFT(Tabela1[[#This Row],[Ref.]],4),RIGHT(Tabela1[[#This Row],[Ref.]],2),1),"") | AD18: =IF($H18<>"",$F18,"") | AE18: =IF($H18<>"",$G18,"") | AG18: =IF($H18<>"",$B$2,"")
R19: =IF($H19<>"",RIGHT(Tabela1[[#This Row],[Ref.]],2),"") | S19: =IF($H19<>"",1,"") | T19: =IF($H19<>"",_xlfn.XLOOKUP(H19,Naturezas!B:B,Naturezas!E:E,"",0,1),"") | U19: =IF($H19<>"",_xlfn.XLOOKUP($H19,Naturezas!B:B,Naturezas!D:D,"",0,1),"") | V19: =IF(H19<>"",IF(OR(H19=Naturezas!$B$3,H19=Naturezas!$B$4,H19=Naturezas!$B$5,H19=Naturezas!$B$17,H19=Naturezas!$B$18,H19=Naturezas!$B$19),G19,-G19),"") | W19: =IF(H19<>"",H19,"") | Y19: =IF(H19<>"",F19,"") | Z19: =IF(H19<>"",Tabela1[[#This Row],[Iniciais]],"") | AB19: =IF($H19<>"",RIGHT(Tabela1[[#This Row],[Ref.]],2),"") | AC19: =IF($H19<>"",DATE(LEFT(Tabela1[[#This Row],[Ref.]],4),RIGHT(Tabela1[[#This Row],[Ref.]],2),1),"") | AD19: =IF($H19<>"",$F19,"") | AE19: =IF($H19<>"",$G19,"") | AG19: =IF($H19<>"",$B$2,"")
R20: =IF($H20<>"",RIGHT(Tabela1[[#This Row],[Ref.]],2),"") | S20: =IF($H20<>"",1,"") | T20: =IF($H20<>"",_xlfn.XLOOKUP(H20,Naturezas!B:B,Naturezas!E:E,"",0,1),"") | U20: =IF($H20<>"",_xlfn.XLOOKUP($H20,Naturezas!B:B,Naturezas!D:D,"",0,1),"") | V20: =IF(H20<>"",IF(OR(H20=Naturezas!$B$3,H20=Naturezas!$B$4,H20=Naturezas!$B$5,H20=Naturezas!$B$17,H20=Naturezas!$B$18,H20=Naturezas!$B$19),G20,-G20),"") | W20: =IF(H20<>"",H20,"") | Y20: =IF(H20<>"",F20,"") | Z20: =IF(H20<>"",Tabela1[[#This Row],[Iniciais]],"") | AB20: =IF($H20<>"",RIGHT(Tabela1[[#This Row],[Ref.]],2),"") | AC20: =IF($H20<>"",DATE(LEFT(Tabela1[[#This Row],[Ref.]],4),RIGHT(Tabela1[[#This Row],[Ref.]],2),1),"") | AD20: =IF($H20<>"",$F20,"") | AE20: =IF($H20<>"",$G20,"") | AG20: =IF($H20<>"",$B$2,"")
R21: =IF($H21<>"",RIGHT(Tabela1[[#This Row],[Ref.]],2),"") | S21: =IF($H21<>"",1,"") | T21: =IF($H21<>"",_xlfn.XLOOKUP(H21,Naturezas!B:B,Naturezas!E:E,"",0,1),"") | U21: =IF($H21<>"",_xlfn.XLOOKUP($H21,Naturezas!B:B,Naturezas!D:D,"",0,1),"") | V21: =IF(H21<>"",IF(OR(H21=Naturezas!$B$3,H21=Naturezas!$B$4,H21=Naturezas!$B$5,H21=Naturezas!$B$17,H21=Naturezas!$B$18,H21=Naturezas!$B$19),G21,-G21),"") | W21: =IF(H21<>"",H21,"") | Y21: =IF(H21<>"",F21,"") | Z21: =IF(H21<>"",Tabela1[[#This Row],[Iniciais]],"") | AB21: =IF($H21<>"",RIGHT(Tabela1[[#This Row],[Ref.]],2),"") | AC21: =IF($H21<>"",DATE(LEFT(Tabela1[[#This Row],[Ref.]],4),RIGHT(Tabela1[[#This Row],[Ref.]],2),1),"") | AD21: =IF($H21<>"",$F21,"") | AE21: =IF($H21<>"",$G21,"") | AG21: =IF($H21<>"",$B$2,"")
... R62: =IF($H62<>"",RIGHT(Tabela1[[#This Row],[Ref.]],2),"") | S62: =IF($H62<>"",1,"") | T62: =IF($H62<>"",_xlfn.XLOOKUP(H62,Naturezas!B:B,Naturezas!E:E,"",0,1),"") | U62: =IF($H62<>"",_xlfn.XLOOKUP($H62,Naturezas!B:B,Naturezas!D:D,"",0,1),"") | V62: =IF(H62<>"",IF(OR(H62=Naturezas!$B$3,H62=Naturezas!$B$4,H62=Naturezas!$B$5,H62=Naturezas!$B$17,H62=Naturezas!$B$18,H62=Naturezas!$B$19),G62,-G62),"") | W62: =IF(H62<>"",H62,"") | Y62: =IF(H62<>"",F62,"") | Z62: =IF(H62<>"",Tabela1[[#This Row],[Iniciais]],"") | AB62: =IF($H62<>"",RIGHT(Tabela1[[#This Row],[Ref.]],2),"") | AC62: =IF($H62<>"",DATE(LEFT(Tabela1[[#This Row],[Ref.]],4),RIGHT(Tabela1[[#This Row],[Ref.]],2),1),"") | AD62: =IF($H62<>"",$F62,"") | AE62: =IF($H62<>"",$G62,"") | AG62: =IF($H62<>"",$B$2,"")
R63: =IF($H63<>"",RIGHT(Tabela1[[#This Row],[Ref.]],2),"") | S63: =IF($H63<>"",1,"") | T63: =IF($H63<>"",_xlfn.XLOOKUP(H63,Naturezas!B:B,Naturezas!E:E,"",0,1),"") | U63: =IF($H63<>"",_xlfn.XLOOKUP($H63,Naturezas!B:B,Naturezas!D:D,"",0,1),"") | V63: =IF(H63<>"",IF(OR(H63=Naturezas!$B$3,H63=Naturezas!$B$4,H63=Naturezas!$B$5,H63=Naturezas!$B$17,H63=Naturezas!$B$18,H63=Naturezas!$B$19),G63,-G63),"") | W63: =IF(H63<>"",H63,"") | Y63: =IF(H63<>"",F63,"") | Z63: =IF(H63<>"",Tabela1[[#This Row],[Iniciais]],"") | AB63: =IF($H63<>"",RIGHT(Tabela1[[#This Row],[Ref.]],2),"") | AC63: =IF($H63<>"",DATE(LEFT(Tabela1[[#This Row],[Ref.]],4),RIGHT(Tabela1[[#This Row],[Ref.]],2),1),"") | AD63: =IF($H63<>"",$F63,"") | AE63: =IF($H63<>"",$G63,"") | AG63: =IF($H63<>"",$B$2,"") | AK63: Saldo cc | AL63: Aplic
R64: =IF($H64<>"",RIGHT(Tabela1[[#This Row],[Ref.]],2),"") | S64: =IF($H64<>"",1,"") | T64: =IF($H64<>"",_xlfn.XLOOKUP(H64,Naturezas!B:B,Naturezas!E:E,"",0,1),"") | U64: =IF($H64<>"",_xlfn.XLOOKUP($H64,Naturezas!B:B,Naturezas!D:D,"",0,1),"") | V64: =IF(H64<>"",IF(OR(H64=Naturezas!$B$3,H64=Naturezas!$B$4,H64=Naturezas!$B$5,H64=Naturezas!$B$17,H64=Naturezas!$B$18,H64=Naturezas!$B$19),G64,-G64),"") | W64: =IF(H64<>"",H64,"") | Y64: =IF(H64<>"",F64,"") | Z64: =IF(H64<>"",Tabela1[[#This Row],[Iniciais]],"") | AB64: =IF($H64<>"",RIGHT(Tabela1[[#This Row],[Ref.]],2),"") | AC64: =IF($H64<>"",DATE(LEFT(Tabela1[[#This Row],[Ref.]],4),RIGHT(Tabela1[[#This Row],[Ref.]],2),1),"") | AD64: =IF($H64<>"",$F64,"") | AE64: =IF($H64<>"",$G64,"") | AG64: =IF($H64<>"",$B$2,"") | AK64: 198.48 | AL64: 279.94
R65: =IF($H65<>"",RIGHT(Tabela1[[#This Row],[Ref.]],2),"") | S65: =IF($H65<>"",1,"") | T65: =IF($H65<>"",_xlfn.XLOOKUP(H65,Naturezas!B:B,Naturezas!E:E,"",0,1),"") | U65: =IF($H65<>"",_xlfn.XLOOKUP($H65,Naturezas!B:B,Naturezas!D:D,"",0,1),"") | V65: =IF(H65<>"",IF(OR(H65=Naturezas!$B$3,H65=Naturezas!$B$4,H65=Naturezas!$B$5,H65=Naturezas!$B$17,H65=Naturezas!$B$18,H65=Naturezas!$B$19),G65,-G65),"") | W65: =IF(H65<>"",H65,"") | Y65: =IF(H65<>"",F65,"") | Z65: =IF(H65<>"",Tabela1[[#This Row],[Iniciais]],"") | AB65: =IF($H65<>"",RIGHT(Tabela1[[#This Row],[Ref.]],2),"") | AC65: =IF($H65<>"",DATE(LEFT(Tabela1[[#This Row],[Ref.]],4),RIGHT(Tabela1[[#This Row],[Ref.]],2),1),"") | AD65: =IF($H65<>"",$F65,"") | AE65: =IF($H65<>"",$G65,"") | AG65: =IF($H65<>"",$B$2,"")
R66: =IF($H66<>"",RIGHT(Tabela1[[#This Row],[Ref.]],2),"") | S66: =IF($H66<>"",1,"") | T66: =IF($H66<>"",_xlfn.XLOOKUP(H66,Naturezas!B:B,Naturezas!E:E,"",0,1),"") | U66: =IF($H66<>"",_xlfn.XLOOKUP($H66,Naturezas!B:B,Naturezas!D:D,"",0,1),"") | V66: =IF(H66<>"",IF(OR(H66=Naturezas!$B$3,H66=Naturezas!$B$4,H66=Naturezas!$B$5,H66=Naturezas!$B$17,H66=Naturezas!$B$18,H66=Naturezas!$B$19),G66,-G66),"") | W66: =IF(H66<>"",H66,"") | Y66: =IF(H66<>"",F66,"") | Z66: =IF(H66<>"",Tabela1[[#This Row],[Iniciais]],"") | AB66: =IF($H66<>"",RIGHT(Tabela1[[#This Row],[Ref.]],2),"") | AC66: =IF($H66<>"",DATE(LEFT(Tabela1[[#This Row],[Ref.]],4),RIGHT(Tabela1[[#This Row],[Ref.]],2),1),"") | AD66: =IF($H66<>"",$F66,"") | AE66: =IF($H66<>"",$G66,"") | AG66: =IF($H66<>"",$B$2,"")
R67: =IF($H67<>"",RIGHT(Tabela1[[#This Row],[Ref.]],2),"") | S67: =IF($H67<>"",1,"") | T67: =IF($H67<>"",_xlfn.XLOOKUP(H67,Naturezas!B:B,Naturezas!E:E,"",0,1),"") | U67: =IF($H67<>"",_xlfn.XLOOKUP($H67,Naturezas!B:B,Naturezas!D:D,"",0,1),"") | V67: =IF(H67<>"",IF(OR(H67=Naturezas!$B$3,H67=Naturezas!$B$4,H67=Naturezas!$B$5,H67=Naturezas!$B$17,H67=Naturezas!$B$18,H67=Naturezas!$B$19),G67,-G67),"") | W67: =IF(H67<>"",H67,"") | Y67: =IF(H67<>"",F67,"") | Z67: =IF(H67<>"",Tabela1[[#This Row],[Iniciais]],"") | AB67: =IF($H67<>"",RIGHT(Tabela1[[#This Row],[Ref.]],2),"") | AC67: =IF($H67<>"",DATE(LEFT(Tabela1[[#This Row],[Ref.]],4),RIGHT(Tabela1[[#This Row],[Ref.]],2),1),"") | AD67: =IF($H67<>"",$F67,"") | AE67: =IF($H67<>"",$G67,"") | AG67: =IF($H67<>"",$B$2,"")
R68: =IF($H68<>"",RIGHT(Tabela1[[#This Row],[Ref.]],2),"") | S68: =IF($H68<>"",1,"") | T68: =IF($H68<>"",_xlfn.XLOOKUP(H68,Naturezas!B:B,Naturezas!E:E,"",0,1),"") | U68: =IF($H68<>"",_xlfn.XLOOKUP($H68,Naturezas!B:B,Naturezas!D:D,"",0,1),"") | V68: =IF(H68<>"",IF(OR(H68=Naturezas!$B$3,H68=Naturezas!$B$4,H68=Naturezas!$B$5,H68=Naturezas!$B$17,H68=Naturezas!$B$18,H68=Naturezas!$B$19),G68,-G68),"") | W68: =IF(H68<>"",H68,"") | Y68: =IF(H68<>"",F68,"") | Z68: =IF(H68<>"",Tabela1[[#This Row],[Iniciais]],"") | AB68: =IF($H68<>"",RIGHT(Tabela1[[#This Row],[Ref.]],2),"") | AC68: =IF($H68<>"",DATE(LEFT(Tabela1[[#This Row],[Ref.]],4),RIGHT(Tabela1[[#This Row],[Ref.]],2),1),"") | AD68: =IF($H68<>"",$F68,"") | AE68: =IF($H68<>"",$G68,"") | AG68: =IF($H68<>"",$B$2,"")
R69: =IF($H69<>"",RIGHT(Tabela1[[#This Row],[Ref.]],2),"") | S69: =IF($H69<>"",1,"") | T69: =IF($H69<>"",_xlfn.XLOOKUP(H69,Naturezas!B:B,Naturezas!E:E,"",0,1),"") | U69: =IF($H69<>"",_xlfn.XLOOKUP($H69,Naturezas!B:B,Naturezas!D:D,"",0,1),"") | V69: =IF(H69<>"",IF(OR(H69=Naturezas!$B$3,H69=Naturezas!$B$4,H69=Naturezas!$B$5,H69=Naturezas!$B$17,H69=Naturezas!$B$18,H69=Naturezas!$B$19),G69,-G69),"") | W69: =IF(H69<>"",H69,"") | Y69: =IF(H69<>"",F69,"") | Z69: =IF(H69<>"",Tabela1[[#This Row],[Iniciais]],"") | AB69: =IF($H69<>"",RIGHT(Tabela1[[#This Row],[Ref.]],2),"") | AC69: =IF($H69<>"",DATE(LEFT(Tabela1[[#This Row],[Ref.]],4),RIGHT(Tabela1[[#This Row],[Ref.]],2),1),"") | AD69: =IF($H69<>"",$F69,"") | AE69: =IF($H69<>"",$G69,"") | AG69: =IF($H69<>"",$B$2,"")
R70: =IF($H70<>"",RIGHT(Tabela1[[#This Row],[Ref.]],2),"") | S70: =IF($H70<>"",1,"") | T70: =IF($H70<>"",_xlfn.XLOOKUP(H70,Naturezas!B:B,Naturezas!E:E,"",0,1),"") | U70: =IF($H70<>"",_xlfn.XLOOKUP($H70,Naturezas!B:B,Naturezas!D:D,"",0,1),"") | V70: =IF(H70<>"",IF(OR(H70=Naturezas!$B$3,H70=Naturezas!$B$4,H70=Naturezas!$B$5,H70=Naturezas!$B$17,H70=Naturezas!$B$18,H70=Naturezas!$B$19),G70,-G70),"") | W70: =IF(H70<>"",H70,"") | Y70: =IF(H70<>"",F70,"") | Z70: =IF(H70<>"",Tabela1[[#This Row],[Iniciais]],"") | AB70: =IF($H70<>"",RIGHT(Tabela1[[#This Row],[Ref.]],2),"") | AC70: =IF($H70<>"",DATE(LEFT(Tabela1[[#This Row],[Ref.]],4),RIGHT(Tabela1[[#This Row],[Ref.]],2),1),"") | AD70: =IF($H70<>"",$F70,"") | AE70: =IF($H70<>"",$G70,"") | AG70: =IF($H70<>"",$B$2,"")
R71: =IF($H71<>"",RIGHT(Tabela1[[#This Row],[Ref.]],2),"") | S71: =IF($H71<>"",1,"") | T71: =IF($H71<>"",_xlfn.XLOOKUP(H71,Naturezas!B:B,Naturezas!E:E,"",0,1),"") | U71: =IF($H71<>"",_xlfn.XLOOKUP($H71,Naturezas!B:B,Naturezas!D:D,"",0,1),"") | V71: =IF(H71<>"",IF(OR(H71=Naturezas!$B$3,H71=Naturezas!$B$4,H71=Naturezas!$B$5,H71=Naturezas!$B$17,H71=Naturezas!$B$18,H71=Naturezas!$B$19),G71,-G71),"") | W71: =IF(H71<>"",H71,"") | Y71: =IF(H71<>"",F71,"") | Z71: =IF(H71<>"",Tabela1[[#This Row],[Iniciais]],"") | AB71: =IF($H71<>"",RIGHT(Tabela1[[#This Row],[Ref.]],2),"") | AC71: =IF($H71<>"",DATE(LEFT(Tabela1[[#This Row],[Ref.]],4),RIGHT(Tabela1[[#This Row],[Ref.]],2),1),"") | AD71: =IF($H71<>"",$F71,"") | AE71: =IF($H71<>"",$G71,"") | AG71: =IF($H71<>"",$B$2,"")
R72: =IF($H72<>"",RIGHT(Tabela1[[#This Row],[Ref.]],2),"") | S72: =IF($H72<>"",1,"") | T72: =IF($H72<>"",_xlfn.XLOOKUP(H72,Naturezas!B:B,Naturezas!E:E,"",0,1),"") | U72: =IF($H72<>"",_xlfn.XLOOKUP($H72,Naturezas!B:B,Naturezas!D:D,"",0,1),"") | V72: =IF(H72<>"",IF(OR(H72=Naturezas!$B$3,H72=Naturezas!$B$4,H72=Naturezas!$B$5,H72=Naturezas!$B$17,H72=Naturezas!$B$18,H72=Naturezas!$B$19),G72,-G72),"") | W72: =IF(H72<>"",H72,"") | Y72: =IF(H72<>"",F72,"") | Z72: =IF(H72<>"",Tabela1[[#This Row],[Iniciais]],"") | AB72: =IF($H72<>"",RIGHT(Tabela1[[#This Row],[Ref.]],2),"") | AC72: =IF($H72<>"",DATE(LEFT(Tabela1[[#This Row],[Ref.]],4),RIGHT(Tabela1[[#This Row],[Ref.]],2),1),"") | AD72: =IF($H72<>"",$F72,"") | AE72: =IF($H72<>"",$G72,"") | AG72: =IF($H72<>"",$B$2,"")
R73: =IF($H73<>"",RIGHT(Tabela1[[#This Row],[Ref.]],2),"") | S73: =IF($H73<>"",1,"") | T73: =IF($H73<>"",_xlfn.XLOOKUP(H73,Naturezas!B:B,Naturezas!E:E,"",0,1),"") | U73: =IF($H73<>"",_xlfn.XLOOKUP($H73,Naturezas!B:B,Naturezas!D:D,"",0,1),"") | V73: =IF(H73<>"",IF(OR(H73=Naturezas!$B$3,H73=Naturezas!$B$4,H73=Naturezas!$B$5,H73=Naturezas!$B$17,H73=Naturezas!$B$18,H73=Naturezas!$B$19),G73,-G73),"") | W73: =IF(H73<>"",H73,"") | Y73: =IF(H73<>"",F73,"") | Z73: =IF(H73<>"",Tabela1[[#This Row],[Iniciais]],"") | AB73: =IF($H73<>"",RIGHT(Tabela1[[#This Row],[Ref.]],2),"") | AC73: =IF($H73<>"",DATE(LEFT(Tabela1[[#This Row],[Ref.]],4),RIGHT(Tabela1[[#This Row],[Ref.]],2),1),"") | AD73: =IF($H73<>"",$F73,"") | AE73: =IF($H73<>"",$G73,"") | AG73: =IF($H73<>"",$B$2,"")
R74: =IF($H74<>"",RIGHT(Tabela1[[#This Row],[Ref.]],2),"") | S74: =IF($H74<>"",1,"") | T74: =IF($H74<>"",_xlfn.XLOOKUP(H74,Naturezas!B:B,Naturezas!E:E,"",0,1),"") | U74: =IF($H74<>"",_xlfn.XLOOKUP($H74,Naturezas!B:B,Naturezas!D:D,"",0,1),"") | V74: =IF(H74<>"",IF(OR(H74=Naturezas!$B$3,H74=Naturezas!$B$4,H74=Naturezas!$B$5,H74=Naturezas!$B$17,H74=Naturezas!$B$18,H74=Naturezas!$B$19),G74,-G74),"") | W74: =IF(H74<>"",H74,"") | Y74: =IF(H74<>"",F74,"") | Z74: =IF(H74<>"",Tabela1[[#This Row],[Iniciais]],"") | AB74: =IF($H74<>"",RIGHT(Tabela1[[#This Row],[Ref.]],2),"") | AC74: =IF($H74<>"",DATE(LEFT(Tabela1[[#This Row],[Ref.]],4),RIGHT(Tabela1[[#This Row],[Ref.]],2),1),"") | AD74: =IF($H74<>"",$F74,"") | AE74: =IF($H74<>"",$G74,"") | AG74: =IF($H74<>"",$B$2,"")
R75: =IF($H75<>"",RIGHT(Tabela1[[#This Row],[Ref.]],2),"") | S75: =IF($H75<>"",1,"") | T75: =IF($H75<>"",_xlfn.XLOOKUP(H75,Naturezas!B:B,Naturezas!E:E,"",0,1),"") | U75: =IF($H75<>"",_xlfn.XLOOKUP($H75,Naturezas!B:B,Naturezas!D:D,"",0,1),"") | V75: =IF(H75<>"",IF(OR(H75=Naturezas!$B$3,H75=Naturezas!$B$4,H75=Naturezas!$B$5,H75=Naturezas!$B$17,H75=Naturezas!$B$18,H75=Naturezas!$B$19),G75,-G75),"") | W75: =IF(H75<>"",H75,"") | Y75: =IF(H75<>"",F75,"") | Z75: =IF(H75<>"",Tabela1[[#This Row],[Iniciais]],"") | AB75: =IF($H75<>"",RIGHT(Tabela1[[#This Row],[Ref.]],2),"") | AC75: =IF($H75<>"",DATE(LEFT(Tabela1[[#This Row],[Ref.]],4),RIGHT(Tabela1[[#This Row],[Ref.]],2),1),"") | AD75: =IF($H75<>"",$F75,"") | AE75: =IF($H75<>"",$G75,"") | AG75: =IF($H75<>"",$B$2,"")
R76: =IF($H76<>"",RIGHT(Tabela1[[#This Row],[Ref.]],2),"") | S76: =IF($H76<>"",1,"") | T76: =IF($H76<>"",_xlfn.XLOOKUP(H76,Naturezas!B:B,Naturezas!E:E,"",0,1),"") | U76: =IF($H76<>"",_xlfn.XLOOKUP($H76,Naturezas!B:B,Naturezas!D:D,"",0,1),"") | V76: =IF(H76<>"",IF(OR(H76=Naturezas!$B$3,H76=Naturezas!$B$4,H76=Naturezas!$B$5,H76=Naturezas!$B$17,H76=Naturezas!$B$18,H76=Naturezas!$B$19),G76,-G76),"") | W76: =IF(H76<>"",H76,"") | Y76: =IF(H76<>"",F76,"") | Z76: =IF(H76<>"",Tabela1[[#This Row],[Iniciais]],"") | AB76: =IF($H76<>"",RIGHT(Tabela1[[#This Row],[Ref.]],2),"") | AC76: =IF($H76<>"",DATE(LEFT(Tabela1[[#This Row],[Ref.]],4),RIGHT(Tabela1[[#This Row],[Ref.]],2),1),"") | AD76: =IF($H76<>"",$F76,"") | AE76: =IF($H76<>"",$G76,"") | AG76: =IF($H76<>"",$B$2,"")
... R504: =IF($H504<>"",RIGHT(Tabela1[[#This Row],[Ref.]],2),"") | S504: =IF($H504<>"",1,"") | T504: =IF($H504<>"",_xlfn.XLOOKUP(H504,Naturezas!B:B,Naturezas!E:E,"",0,1),"") | U504: =IF($H504<>"",_xlfn.XLOOKUP($H504,Naturezas!B:B,Naturezas!D:D,"",0,1),"") | V504: =IF(H504<>"",IF(OR(H504=Naturezas!$B$3,H504=Naturezas!$B$4,H504=Naturezas!$B$5,H504=Naturezas!$B$17,H504=Naturezas!$B$18,H504=Naturezas!$B$19),G504,-G504),"") | W504: =IF(H504<>"",H504,"") | Y504: =IF(H504<>"",F504,"") | Z504: =IF(H504<>"",Tabela1[[#This Row],[Iniciais]],"") | AB504: =IF($H504<>"",RIGHT(Tabela1[[#This Row],[Ref.]],2),"") | AC504: =IF($H504<>"",DATE(LEFT(Tabela1[[#This Row],[Ref.]],4),RIGHT(Tabela1[[#This Row],[Ref.]],2),1),"") | AD504: =IF($H504<>"",$F504,"") | AE504: =IF($H504<>"",$G504,"") | AG504: =IF($H504<>"",$B$2,"")

Sheet Dicionario

Sheet Naturezas
A1: Suporte
A2: Natureza | B2: Natureza | C2: E/S | D2: Dados de apoio | E2: Dados de apoio | F2: Descrição curta
A3: Residentes | B3: RR | C3: entrada | D3: E | E3: B | F3: Receitas e despesas vinculadas ao trabalho profissional e previdência privada
A4: Adjuntos | B4: AR | C4: entrada | D4: E | E4: B
A5: Subvenções | B5: DN | C5: entrada | D5: E | E5: B
A6: Pensões | B6: PS | C6: saída | D6: S | E6: B
A7: Gastos Ordinários | B7: GO | C7: saída | D7: S | E7: B | F7: Gastos ordinários (assinaturas, transporte, refeições, etc.)
A8: Roupas | B8: RP | C8: saída | D8: S | E8: B | F8: Gastos com roupas, sapatos, indumentária em geral
A9: Médicos e Remédios | B9: MR | C9: saída | D9: S | E9: B | F9: Gastos com consultas, exames, remédios, tratamentos, plano de saúde etc.
A10: Diversos Pessoais | B10: DV | C10: saída | D10: S | E10: B | F10: Gastos com cursos anuais, convívios, retiros, viagens, despesas extraordinárias etc.
A11: Adjuntos | B11: AD | C11: saída | D11: S | E11: B
A12: Veículos | B12: VC | C12: saída | D12: S | E12: B | F12: Gastos com combustível, pedágio, limpeza, manutenção, etc.
A13: Natal e Festas | B13: NF | C13: saída | D13: S | E13: B
A14: Vários | B14: VR | C14: saída | D14: S | E14: B | F14: Materiais de escritório, Farmácia da Casa
A15: Donativos ao Centro | B15: DC | C15: saída | D15: S | E15: B
A16: Contrib. labores ap. | B16: DL | C16: saída | D16: S | E16: B | F16: Subvenções e doações para iniciativas apostólicas, ajudas familiares etc.
A17: Contribuição de residentes | B17: CO | C17: entrada | D17: E | E17: C
A18: Contribuições participantes | B18: CP | C18: entrada | D18: E | E18: C
A19: Outros conceitos | B19: OT | C19: entrada | D19: E | E19: C
A20: IPTU e Seguros | B20: CF | C20: saída | D20: S | E20: C
A21: Ordenados | B21: OR | C21: saída | D21: S | E21: C | F21: Pagamento de ordenados
A22: Comestíveis | B22: CM | C22: saída | D22: S | E22: C | F22: Pagamento de despesas com comestiveis para a casa em geral
A23: Gastos Gerais | B23: GG | C23: saída | D23: S | E23: C
A24: Luz | B24: LZ | C24: saída | D24: S | E24: C | F24: Conta de energia
A25: Água | B25: AG | C25: saída | D25: S | E25: C | F25: Conta de água
A26: Gás | B26: GS | C26: saída | D26: S | E26: C | F26: Conta de gás
A27: Telefone | B27: TF | C27: saída | D27: S | E27: C | F27: Conta de internet e telefonia
A28: Consertos | B28: CS | C28: saída | D28: S | E28: C | F28: Custos com manutenção
A29: Manutenção/Reposição | B29: MT | C29: saída | D29: S | E29: C | F29: Custos com jardinagem, faxina, materiais de limpeza, peças e insumos para manutenção etc.
A30: Vários | B30: VR | C30: saída | D30: S | E30: C
A31: Atividades culturais | B31: AC | C31: saída | D31: S | E31: C
A32: Instalações | B32: IT | C32: saída | D32: S | E32: C | F32: Custos para consertos e melhorias em geral nas instalações da casa
